flet_pages/__init__.py
flet_pages/i18n.py
flet_pages/router/__init__.py
flet_pages/router/page_meta.py
flet_pages/tests/__init__.py
flet_pages/tests/main.py
flet_pages/tests/pages/__init__.py
flet_pages/tests/pages/about.py
flet_pages/tests/pages/start.py
flet_pages-0.0.2.dist-info/METADATA
flet_pages-0.0.2.dist-info/WHEEL
flet_pages-0.0.2.dist-info/licenses/LICENSE
flet_pages-0.0.2.dist-info/RECORD
