Metadata-Version: 2.4
Name: flet_pages
Version: 0.0.2
Summary: Flet Pages Router And I18n
License: MIT
License-File: LICENSE
Author: Gudupao
Author-email: official@gudupao.top
Requires-Python: >=3.8
Classifier: License :: OSI Approved :: MIT License
Classifier: Programming Language :: Python :: 3
Classifier: Programming Language :: Python :: 3.8
Classifier: Programming Language :: Python :: 3.9
Classifier: Programming Language :: Python :: 3.10
Classifier: Programming Language :: Python :: 3.11
Classifier: Programming Language :: Python :: 3.12
Classifier: Programming Language :: Python :: 3.13
Classifier: Programming Language :: Python :: 3.14
Requires-Dist: flet[all]
